{
  "@odata.etag": "",
  "id": "bc_line_id",
  "documentId": "sales_order_id",
  "sequence": "",
  "itemId": "",
  "accountId": "",
  "lineType": "",
  "lineObjectNumber": "",
  "description": "name",
  "description2": "",
  "unitOfMeasureId": "",
  "unitOfMeasureCode": "",
  "quantity": "quantity",
  "unitPrice": "price",
  "discountAmount": "",
  "discountPercent": "",
  "discountAppliedBeforeTax": "",
  "amountExcludingTax": "",
  "taxCode": "",
  "taxPercent": "",
  "totalTaxAmount": "",
  "amountIncludingTax": "",
  "invoiceDiscountAllocation": "",
  "netAmount": "",
  "netTaxAmount": "",
  "netAmountIncludingTax": "",
  "shipmentDate": "shipment_date",
  "itemVariantId": "hs_sku",
  "locationId": ""
}